Metadata-Version: 2.1
Name: EventSimpleGUI
Version: 0.3.1
Summary: A simple tool to create events to PySimpleGUI
Home-page: https://github.com/MikalROn/EventSimpleGUI
Author: Daniel Coêlho
Author-email: heromon.9010@gmail.com
License: MIT license
Project-URL: Tests, https://smokeshow.helpmanual.io/474z2x1c0s2u3j101i26/
Project-URL: Source, https://github.com/MikalROn/EventSimpleGUI
Project-URL: Demos, https://github.com/MikalROn/EventSimpleGUI/tree/main/demos
Project-URL: Docs, https://mikalron.github.io/EventSimpleGUI/
Keywords: eventsimplegui,EventSimpleGUI,simplegui,GUI,gui,events for simplegui,event handler simple gui,generate events,fast events,events
Platform: UNKNOWN
Requires-Python: >=3
License-File: LICENCE
